trksnapshot/__init__.py
trksnapshot/main.py
trksnapshot-0.1.5.dist-info/licenses/LICENSE
trksnapshot-0.1.5.dist-info/METADATA
trksnapshot-0.1.5.dist-info/WHEEL
trksnapshot-0.1.5.dist-info/entry_points.txt
trksnapshot-0.1.5.dist-info/top_level.txt
trksnapshot-0.1.5.dist-info/RECORD
