Metadata-Version: 2.4
Name: trksnapshot
Version: 0.1.5
Summary: Tractometry Visualization Tool
Author-email: Yixue Wendy Feng <yixuewendy.f@gmail.com>
License: MIT License
Project-URL: Homepage, https://github.com/wendyfyx/trksnapshot
Project-URL: Issues, https://github.com/wendyfyx/trksnapshot/issues
Keywords: tractometry,tractography,diffusion MRI,white matter
Classifier: Development Status :: 4 - Beta
Classifier: Intended Audience :: Developers
Classifier: Intended Audience :: Science/Research
Classifier: Programming Language :: Python :: 3
Classifier: Programming Language :: Python :: 3.10
Classifier: License :: OSI Approved :: MIT License
Classifier: Operating System :: OS Independent
Requires-Python: >=3.10
License-File: LICENSE
Requires-Dist: matplotlib>=3.7.0
Requires-Dist: dipy==1.9.0
Requires-Dist: fury>=0.10.0
Requires-Dist: opencv-python>4.9.0.80
Requires-Dist: nilearn==0.11.1
Requires-Dist: numpy==1.26.4
Dynamic: license-file
